[
    {
        "UPDATE": [
            {
                "operation": "DEL",
                "internal_id": "3b85e59e79f7447da9289275dfbc9abf",
                "feature_name": "extendedBy",
                "feature_value": [
                    "dc3e046f6e744dc98426221e5b208a07"
                ]
            }
        ]
    },
    {
        "DELETE": [
            {
                "operation": "DEL",
                "internal_id": "dc3e046f6e744dc98426221e5b208a07",
                "file_source_xmi": "<?xml version='1.0' encoding='UTF-8'?>\n<OO:Class xmlns:xmi=\"http://www.omg.org/XMI\" xmlns:OO=\"OO\" xmlns:xsi=\"http://www.w3.org/2001/XMLSchema-instance\" xmi:id=\"dc3e046f6e744dc98426221e5b208a07\" name=\"student\" xmi:version=\"2.0\">\n  <extends href=\"C:/Users/Admin/Desktop/VSM/server_last_version.xmi#3b85e59e79f7447da9289275dfbc9abf\" xsi:type=\"OO:Class\"/>\n</OO:Class>\n",
                "element_References": [
                    {
                        "feature_name": "package",
                        "feature_value": "c29ae9b3f98c43b9b9c702ea51ea72d6"
                    },
                    {
                        "feature_name": "extends",
                        "feature_value": "3b85e59e79f7447da9289275dfbc9abf"
                    }
                ]
            }
        ]
    },
    {
        "ADD": []
    }
]